README.md
setup.cfg
setup.py
batch_microsoft_translator/__init__.py
batch_microsoft_translator/batch_microsoft_translator.py
batch_microsoft_translator.egg-info/PKG-INFO
batch_microsoft_translator.egg-info/SOURCES.txt
batch_microsoft_translator.egg-info/dependency_links.txt
batch_microsoft_translator.egg-info/requires.txt
batch_microsoft_translator.egg-info/top_level.txt