Metadata-Version: 2.1
Name: batch-microsoft-translator
Version: 0.0.1
Summary: Make large amounts of translations using microsoft translator reliably
Home-page: https://github.com/TheTallBlonde1/batch_microsoft_translator
Author: Stefan Selby
Author-email: stefanselby@gmail.com
License: MIT
Download-URL: https://github.com/TheTallBlonde1/batch_microsoft_translator/archive/v_0_0_1.tar.gz
Keywords: MICROSOFT,TRANSLATOR,TRANSLATION,COGNITIVE SERVICES
Platform: UNKNOWN
Classifier: Programming Language :: Python :: 3
Classifier: License :: Public Domain
Classifier: Operating System :: OS Independent
